monawhat/__init__.py
monawhat/base.py
monawhat/either.py
monawhat/identity.py
monawhat/io.py
monawhat/maybe.py
monawhat/py.typed
monawhat/reader.py
monawhat/state.py
monawhat/writer.py
monawhat-0.1.1.dist-info/METADATA
monawhat-0.1.1.dist-info/WHEEL
monawhat-0.1.1.dist-info/licenses/LICENSE
monawhat-0.1.1.dist-info/RECORD
