Metadata-Version: 2.4
Name: monawhat
Version: 0.1.1
Summary: A modern, fully type-hinted, and comprehensively tested monad library for Python 3.11+.
Project-URL: Homepage, https://github.com/dirtyvader/monawhat
Project-URL: Documentation, https://monawhat.readthedocs.io/
Project-URL: Repository, https://github.com/dirtyvader/monawhat
Project-URL: Issues, https://github.com/dirtyvader/monawhat/issues
Author-email: DirtyVader <contact@crad-vador.net>
License-Expression: MIT
License-File: LICENSE
Keywords: educational,functional,functional programming,monad,monads
Classifier: Development Status :: 3 - Alpha
Classifier: Intended Audience :: Developers
Classifier: Intended Audience :: Education
Classifier: License :: OSI Approved :: MIT License
Classifier: Programming Language :: Python :: 3
Classifier: Programming Language :: Python :: 3.11
Classifier: Programming Language :: Python :: 3.12
Classifier: Programming Language :: Python :: 3.13
Classifier: Topic :: Software Development :: Libraries :: Python Modules
Classifier: Typing :: Typed
Requires-Python: >=3.11
